LICENSE
MANIFEST.in
README.md
requirements.txt
setup.py
pynars/Config.py
pynars/Console.py
pynars/Global.py
pynars/__init__.py
pynars/config.json
pynars.egg-info/PKG-INFO
pynars.egg-info/SOURCES.txt
pynars.egg-info/dependency_links.txt
pynars.egg-info/requires.txt
pynars.egg-info/top_level.txt
pynars/NAL/__init__.py
pynars/NAL/_generate_init_file.py
pynars/NAL/Functions/BudgetFunctions.py
pynars/NAL/Functions/DesireValueFunctions.py
pynars/NAL/Functions/ExtendedBooleanFunctions.py
pynars/NAL/Functions/StampFunctions.py
pynars/NAL/Functions/TemporalFunctions.py
pynars/NAL/Functions/Tools.py
pynars/NAL/Functions/TruthValueFunctions.py
pynars/NAL/Functions/UncertaintyMappingFunctions.py
pynars/NAL/Functions/__init__.py
pynars/NAL/Inference/CompositionalRules.py
pynars/NAL/Inference/ConditionalSyllogisticRules.py
pynars/NAL/Inference/ImmediateRules.py
pynars/NAL/Inference/LocalRules.py
pynars/NAL/Inference/SyllogisticRules.py
pynars/NAL/Inference/TemporalRules.py
pynars/NAL/Inference/__init__.py
pynars/NAL/MentalOperation/__init__.py
pynars/NAL/MentalOperation/_aware.py
pynars/NAL/MentalOperation/_execute.py
pynars/NAL/MentalOperation/_register.py
pynars/NAL/MetaLevelInference/GoalDerivation.py
pynars/NAL/MetaLevelInference/QuestionDerivation.py
pynars/NAL/MetaLevelInference/TemporalInference.py
pynars/NAL/MetaLevelInference/__init__.py
pynars/NAL/MetaLevelInference/VariableSubstitution/Elimination.py
pynars/NAL/MetaLevelInference/VariableSubstitution/Introduction.py
pynars/NAL/MetaLevelInference/VariableSubstitution/Substitution.py
pynars/NAL/MetaLevelInference/VariableSubstitution/Unification.py
pynars/NAL/MetaLevelInference/VariableSubstitution/__init__.py
pynars/NAL/Theorems/DecompositionalRules.py
pynars/NAL/Theorems/StructuralRules.py
pynars/NAL/Theorems/TransformRules.py
pynars/NAL/Theorems/__init__.py
pynars/NARS/__init__.py
pynars/NARS/Control/Reasoner.py
pynars/NARS/Control/__init__.py
pynars/NARS/DataStructures/__init__.py
pynars/NARS/DataStructures/_py/Bag.py
pynars/NARS/DataStructures/_py/Buffer.py
pynars/NARS/DataStructures/_py/Channel.py
pynars/NARS/DataStructures/_py/Concept.py
