Metadata-Version: 2.1
Name: pynars
Version: 0.0.2
Summary: An implementation of Non-Axiomatic Reasoning System
Home-page: https://github.com/bowen-xu/PyNARS
Author: Bowen XU
Author-email: xubowen@pku.edu.cn
License: MIT
Keywords: NARS,Non-Axiomatic Reasoning System,NAL,Non-Axiomatic Logic,Narsese
Platform: UNKNOWN
Classifier: Development Status :: 2 - Pre-Alpha
Classifier: Intended Audience :: Developers
Classifier: License :: OSI Approved :: MIT License
Classifier: Natural Language :: English
Classifier: Natural Language :: Chinese (Simplified)
Classifier: Programming Language :: Python :: 3.7
Classifier: Programming Language :: Python :: 3.8
Classifier: Programming Language :: Python :: 3.9
Classifier: Programming Language :: Python :: 3.10
Classifier: Programming Language :: Python :: 3.10
Classifier: Programming Language :: Python :: Implementation :: CPython
Classifier: Programming Language :: Python :: Implementation :: PyPy
Requires-Python: >=3.7.0
License-File: LICENSE
